<configuration>
    <!-- always a good activate OnConsoleStatusListener -->
    <statusListener class="ch.qos.logback.core.status.OnConsoleStatusListener"/>

    <appender name="FILE" class="ch.qos.logback.core.rolling.RollingFileAppender">
        <file>${logDir}/access.log</file>
        <rollingPolicy class="ch.qos.logback.core.rolling.TimeBasedRollingPolicy">
            <fileNamePattern>${logDir}/access.%d{yyyy-MM-dd}.log.gz</fileNamePattern>
            <maxHistory>2</maxHistory>
        </rollingPolicy>

        <encoder>
            <pattern>%h %l %u [%t] "%r" %s %b "%i{Referer}" "%i{User-Agent}" "%D ms"</pattern>
        </encoder>
    </appender>

    <appender-ref ref="FILE"/>
</configuration>
